{
  "101_1001_0_full": {
    "route_id": "101",
    "route_name": "Blue Line Express",
    "route_short_name": "Blue",
    "stop_id": "1001",
    "stop_name": "Central Station",
    "direction_id": "0",
    "trip_type": "full",
    "total_records": 200,
    "time_types": {
      "available": [
        "am_rush",
        "day",
        "night",
        "weekend"
      ],
      "data": {
        "am_rush": {
          "record_count": 30,
          "is_regulatory": true,
          "travel_time_valid": false,
          "topology_flagged": false,
          "topology_critical": false
        },
        "day": {
          "record_count": 60,
          "is_regulatory": true,
          "travel_time_valid": false,
          "topology_flagged": false,
          "topology_critical": false
        },
        "night": {
          "record_count": 60,
          "is_regulatory": true,
          "travel_time_valid": false,
          "topology_flagged": false,
          "topology_critical": false
        },
        "weekend": {
          "record_count": 50,
          "is_regulatory": true,
          "travel_time_valid": false,
          "topology_flagged": false,
          "topology_critical": false
        }
      }
    },
    "gap_info": {
      "has_gap": false,
      "severity": null,
      "violation_type": null,
      "description": null
    },
    "violation_flags": {
      "has_topology_violation": false,
      "has_pattern_violation": false,
      "has_regulatory_violation": true,
      "has_gap_before_this_stop": false,
      "has_any_violation": true,
      "time_types_with_violations": [
        "am_rush",
        "day",
        "night",
        "weekend"
      ]
    },
    "violation_details_by_time_type": {
      "am_rush": {
        "topology": null,
        "pattern": null,
        "regulatory": {
          "severity": "low",
          "proportion": 0.040000000000000036
        },
        "gap": null,
        "travel_time_unreliable": true
      },
      "day": {
        "topology": null,
        "pattern": null,
        "regulatory": {
          "severity": "low",
          "proportion": 0.040000000000000036
        },
        "gap": null,
        "travel_time_unreliable": true
      },
      "night": {
        "topology": null,
        "pattern": null,
        "regulatory": {
          "severity": "low",
          "proportion": 0.040000000000000036
        },
        "gap": null,
        "travel_time_unreliable": true
      },
      "weekend": {
        "topology": null,
        "pattern": null,
        "regulatory": {
          "severity": "low",
          "proportion": 0.040000000000000036
        },
        "gap": null,
        "travel_time_unreliable": true
      }
    },
    "overall_severity": "low"
  },
  "101_1001_0_partial_1": {
    "route_id": "101",
    "route_name": "Blue Line Express",
    "route_short_name": "Blue",
    "stop_id": "1001",
    "stop_name": "Central Station",
    "direction_id": "0",
    "trip_type": "partial_1",
    "total_records": 76,
    "time_types": {
      "available": [
        "am_rush",
        "day",
        "night",
        "weekend"
      ],
      "data": {
        "am_rush": {
          "record_count": 12,
          "is_regulatory": true,
          "travel_time_valid": false,
          "topology_flagged": false,
          "topology_critical": false
        },
        "day": {
          "record_count": 24,
          "is_regulatory": true,
          "travel_time_valid": false,
          "topology_flagged": false,
          "topology_critical": false
        },
        "night": {
          "record_count": 24,
          "is_regulatory": true,
          "travel_time_valid": false,
          "topology_flagged": false,
          "topology_critical": false
        },
        "weekend": {
          "record_count": 16,
          "is_regulatory": true,
          "travel_time_valid": false,
          "topology_flagged": false,
          "topology_critical": false
        }
      }
    },
    "gap_info": {
      "has_gap": false,
      "severity": null,
      "violation_type": null,
      "description": null
    },
    "violation_flags": {
      "has_topology_violation": false,
      "has_pattern_violation": true,
      "has_regulatory_violation": false,
      "has_gap_before_this_stop": false,
      "has_any_violation": true,
      "time_types_with_violations": [
        "am_rush",
        "day",
        "night",
        "weekend"
      ]
    },
    "violation_details_by_time_type": {
      "am_rush": {
        "topology": null,
        "pattern": {
          "severity": "high",
          "proportion": 1.0
        },
        "regulatory": null,
        "gap": null,
        "travel_time_unreliable": true
      },
      "day": {
        "topology": null,
        "pattern": {
          "severity": "high",
          "proportion": 1.0
        },
        "regulatory": null,
        "gap": null,
        "travel_time_unreliable": true
      },
      "night": {
        "topology": null,
        "pattern": {
          "severity": "high",
          "proportion": 1.0
        },
        "regulatory": null,
        "gap": null,
        "travel_time_unreliable": true
      },
      "weekend": {
        "topology": null,
        "pattern": {
          "severity": "high",
          "proportion": 1.0
        },
        "regulatory": null,
        "gap": null,
        "travel_time_unreliable": true
      }
    },
    "overall_severity": "high"
  },
  "101_1001_0_partial_3": {
    "route_id": "101",
    "route_name": "Blue Line Express",
    "route_short_name": "Blue",
    "stop_id": "1001",
    "stop_name": "Central Station",
    "direction_id": "0",
    "trip_type": "partial_3",
    "total_records": 115,
    "time_types": {
      "available": [
        "am_rush",
        "day",
        "night",
        "weekend"
      ],
      "data": {
        "am_rush": {
          "record_count": 18,
          "is_regulatory": true,
          "travel_time_valid": false,
          "topology_flagged": false,
          "topology_critical": false
        },
        "day": {
          "record_count": 36,
          "is_regulatory": true,
          "travel_time_valid": false,
          "topology_flagged": false,
          "topology_critical": false
        },
        "night": {
          "record_count": 36,
          "is_regulatory": true,
          "travel_time_valid": false,
          "topology_flagged": false,
          "topology_critical": false
        },
        "weekend": {
          "record_count": 25,
          "is_regulatory": true,
          "travel_time_valid": false,
          "topology_flagged": false,
          "topology_critical": false
        }
      }
    },
    "gap_info": {
      "has_gap": false,
      "severity": null,
      "violation_type": null,
      "description": null
    },
    "violation_flags": {
      "has_topology_violation": false,
      "has_pattern_violation": false,
      "has_regulatory_violation": false,
      "has_gap_before_this_stop": false,
      "has_any_violation": false,
      "time_types_with_violations": []
    },
    "violation_details_by_time_type": {
      "am_rush": {
        "topology": null,
        "pattern": null,
        "regulatory": null,
        "gap": null,
        "travel_time_unreliable": true
      },
      "day": {
        "topology": null,
        "pattern": null,
        "regulatory": null,
        "gap": null,
        "travel_time_unreliable": true
      },
      "night": {
        "topology": null,
        "pattern": null,
        "regulatory": null,
        "gap": null,
        "travel_time_unreliable": true
      },
      "weekend": {
        "topology": null,
        "pattern": null,
        "regulatory": null,
        "gap": null,
        "travel_time_unreliable": true
      }
    },
    "overall_severity": "none"
  },
  "101_1002_1_full": {
    "route_id": "101",
    "route_name": "Blue Line Express",
    "route_short_name": "Blue",
    "stop_id": "1002",
    "stop_name": "Central Station",
    "direction_id": "1",
    "trip_type": "full",
    "total_records": 208,
    "time_types": {
      "available": [
        "am_rush",
        "day",
        "night",
        "weekend"
      ],
      "data": {
        "am_rush": {
          "record_count": 33,
          "is_regulatory": false,
          "travel_time_valid": false,
          "topology_flagged": false,
          "topology_critical": false
        },
        "day": {
          "record_count": 60,
          "is_regulatory": false,
          "travel_time_valid": false,
          "topology_flagged": false,
          "topology_critical": false
        },
        "night": {
          "record_count": 63,
          "is_regulatory": false,
          "travel_time_valid": false,
          "topology_flagged": false,
          "topology_critical": false
        },
        "weekend": {
          "record_count": 52,
          "is_regulatory": false,
          "travel_time_valid": false,
          "topology_flagged": false,
          "topology_critical": false
        }
      }
    },
    "gap_info": {
      "has_gap": false,
      "severity": null,
      "violation_type": null,
      "description": null
    },
    "violation_flags": {
      "has_topology_violation": false,
      "has_pattern_violation": false,
      "has_regulatory_violation": false,
      "has_gap_before_this_stop": false,
      "has_any_violation": false,
      "time_types_with_violations": []
    },
    "violation_details_by_time_type": {
      "am_rush": {
        "topology": null,
        "pattern": null,
        "regulatory": null,
        "gap": null,
        "travel_time_unreliable": true
      },
      "day": {
        "topology": null,
        "pattern": null,
        "regulatory": null,
        "gap": null,
        "travel_time_unreliable": true
      },
      "night": {
        "topology": null,
        "pattern": null,
        "regulatory": null,
        "gap": null,
        "travel_time_unreliable": true
      },
      "weekend": {
        "topology": null,
        "pattern": null,
        "regulatory": null,
        "gap": null,
        "travel_time_unreliable": true
      }
    },
    "overall_severity": "none"
  },
  "101_1002_1_partial_1": {
    "route_id": "101",
    "route_name": "Blue Line Express",
    "route_short_name": "Blue",
    "stop_id": "1002",
    "stop_name": "Central Station",
    "direction_id": "1",
    "trip_type": "partial_1",
    "total_records": 76,
    "time_types": {
      "available": [
        "am_rush",
        "day",
        "night",
        "weekend"
      ],
      "data": {
        "am_rush": {
          "record_count": 12,
          "is_regulatory": true,
          "travel_time_valid": false,
          "topology_flagged": false,
          "topology_critical": false
        },
        "day": {
          "record_count": 24,
          "is_regulatory": true,
          "travel_time_valid": false,
          "topology_flagged": false,
          "topology_critical": false
        },
        "night": {
          "record_count": 24,
          "is_regulatory": true,
          "travel_time_valid": false,
          "topology_flagged": false,
          "topology_critical": false
        },
        "weekend": {
          "record_count": 16,
          "is_regulatory": true,
          "travel_time_valid": false,
          "topology_flagged": false,
          "topology_critical": false
        }
      }
    },
    "gap_info": {
      "has_gap": false,
      "severity": null,
      "violation_type": null,
      "description": null
    },
    "violation_flags": {
      "has_topology_violation": false,
      "has_pattern_violation": true,
      "has_regulatory_violation": false,
      "has_gap_before_this_stop": false,
      "has_any_violation": true,
      "time_types_with_violations": [
        "am_rush",
        "day",
        "night",
        "weekend"
      ]
    },
    "violation_details_by_time_type": {
      "am_rush": {
        "topology": null,
        "pattern": {
          "severity": "high",
          "proportion": 1.0
        },
        "regulatory": null,
        "gap": null,
        "travel_time_unreliable": true
      },
      "day": {
        "topology": null,
        "pattern": {
          "severity": "high",
          "proportion": 1.0
        },
        "regulatory": null,
        "gap": null,
        "travel_time_unreliable": true
      },
      "night": {
        "topology": null,
        "pattern": {
          "severity": "high",
          "proportion": 1.0
        },
        "regulatory": null,
        "gap": null,
        "travel_time_unreliable": true
      },
      "weekend": {
        "topology": null,
        "pattern": {
          "severity": "high",
          "proportion": 1.0
        },
        "regulatory": null,
        "gap": null,
        "travel_time_unreliable": true
      }
    },
    "overall_severity": "high"
  },
  "101_1002_1_partial_3": {
    "route_id": "101",
    "route_name": "Blue Line Express",
    "route_short_name": "Blue",
    "stop_id": "1002",
    "stop_name": "Central Station",
    "direction_id": "1",
    "trip_type": "partial_3",
    "total_records": 115,
    "time_types": {
      "available": [
        "am_rush",
        "day",
        "night",
        "weekend"
      ],
      "data": {
        "am_rush": {
          "record_count": 18,
          "is_regulatory": true,
          "travel_time_valid": false,
          "topology_flagged": false,
          "topology_critical": false
        },
        "day": {
          "record_count": 36,
          "is_regulatory": true,
          "travel_time_valid": false,
          "topology_flagged": false,
          "topology_critical": false
        },
        "night": {
          "record_count": 36,
          "is_regulatory": true,
          "travel_time_valid": false,
          "topology_flagged": false,
          "topology_critical": false
        },
        "weekend": {
          "record_count": 25,
          "is_regulatory": true,
          "travel_time_valid": false,
          "topology_flagged": false,
          "topology_critical": false
        }
      }
    },
    "gap_info": {
      "has_gap": false,
      "severity": null,
      "violation_type": null,
      "description": null
    },
    "violation_flags": {
      "has_topology_violation": false,
      "has_pattern_violation": false,
      "has_regulatory_violation": false,
      "has_gap_before_this_stop": false,
      "has_any_violation": false,
      "time_types_with_violations": []
    },
    "violation_details_by_time_type": {
      "am_rush": {
        "topology": null,
        "pattern": null,
        "regulatory": null,
        "gap": null,
        "travel_time_unreliable": true
      },
      "day": {
        "topology": null,
        "pattern": null,
        "regulatory": null,
        "gap": null,
        "travel_time_unreliable": true
      },
      "night": {
        "topology": null,
        "pattern": null,
        "regulatory": null,
        "gap": null,
        "travel_time_unreliable": true
      },
      "weekend": {
        "topology": null,
        "pattern": null,
        "regulatory": null,
        "gap": null,
        "travel_time_unreliable": true
      }
    },
    "overall_severity": "none"
  },
  "101_1003_0_full": {
    "route_id": "101",
    "route_name": "Blue Line Express",
    "route_short_name": "Blue",
    "stop_id": "1003",
    "stop_name": "Financial District",
    "direction_id": "0",
    "trip_type": "full",
    "total_records": 200,
    "time_types": {
      "available": [
        "am_rush",
        "day",
        "night",
        "weekend"
      ],
      "data": {
        "am_rush": {
          "record_count": 30,
          "is_regulatory": true,
          "travel_time_valid": true,
          "topology_flagged": false,
          "topology_critical": false
        },
        "day": {
          "record_count": 60,
          "is_regulatory": true,
          "travel_time_valid": true,
          "topology_flagged": false,
          "topology_critical": false
        },
        "night": {
          "record_count": 60,
          "is_regulatory": true,
          "travel_time_valid": true,
          "topology_flagged": false,
          "topology_critical": false
        },
        "weekend": {
          "record_count": 50,
          "is_regulatory": true,
          "travel_time_valid": true,
          "topology_flagged": false,
          "topology_critical": false
        }
      }
    },
    "gap_info": {
      "has_gap": false,
      "severity": null,
      "violation_type": null,
      "description": null
    },
    "violation_flags": {
      "has_topology_violation": false,
      "has_pattern_violation": false,
      "has_regulatory_violation": false,
      "has_gap_before_this_stop": false,
      "has_any_violation": false,
      "time_types_with_violations": []
    },
    "violation_details_by_time_type": {
      "am_rush": {
        "topology": null,
        "pattern": null,
        "regulatory": null,
        "gap": null,
        "travel_time_unreliable": false
      },
      "day": {
        "topology": null,
        "pattern": null,
        "regulatory": null,
        "gap": null,
        "travel_time_unreliable": false
      },
      "night": {
        "topology": null,
        "pattern": null,
        "regulatory": null,
        "gap": null,
        "travel_time_unreliable": false
      },
      "weekend": {
        "topology": null,
        "pattern": null,
        "regulatory": null,
        "gap": null,
        "travel_time_unreliable": false
      }
    },
    "overall_severity": "none"
  },
  "101_1003_0_partial_3": {
    "route_id": "101",
    "route_name": "Blue Line Express",
    "route_short_name": "Blue",
    "stop_id": "1003",
    "stop_name": "Financial District",
    "direction_id": "0",
    "trip_type": "partial_3",
    "total_records": 115,
    "time_types": {
      "available": [
        "am_rush",
        "day",
        "night",
        "weekend"
      ],
      "data": {
        "am_rush": {
          "record_count": 18,
          "is_regulatory": true,
          "travel_time_valid": true,
          "topology_flagged": false,
          "topology_critical": false
        },
        "day": {
          "record_count": 36,
          "is_regulatory": true,
          "travel_time_valid": true,
          "topology_flagged": false,
          "topology_critical": false
        },
        "night": {
          "record_count": 36,
          "is_regulatory": true,
          "travel_time_valid": true,
          "topology_flagged": false,
          "topology_critical": false
        },
        "weekend": {
          "record_count": 25,
          "is_regulatory": true,
          "travel_time_valid": true,
          "topology_flagged": false,
          "topology_critical": false
        }
      }
    },
    "gap_info": {
      "has_gap": false,
      "severity": null,
      "violation_type": null,
      "description": null
    },
    "violation_flags": {
      "has_topology_violation": false,
      "has_pattern_violation": false,
      "has_regulatory_violation": false,
      "has_gap_before_this_stop": false,
      "has_any_violation": false,
      "time_types_with_violations": []
    },
    "violation_details_by_time_type": {
      "am_rush": {
        "topology": null,
        "pattern": null,
        "regulatory": null,
        "gap": null,
        "travel_time_unreliable": false
      },
      "day": {
        "topology": null,
        "pattern": null,
        "regulatory": null,
        "gap": null,
        "travel_time_unreliable": false
      },
      "night": {
        "topology": null,
        "pattern": null,
        "regulatory": null,
        "gap": null,
        "travel_time_unreliable": false
      },
      "weekend": {
        "topology": null,
        "pattern": null,
        "regulatory": null,
        "gap": null,
        "travel_time_unreliable": false
      }
    },
    "overall_severity": "none"
  },
  "101_1004_1_full": {
    "route_id": "101",
    "route_name": "Blue Line Express",
    "route_short_name": "Blue",
    "stop_id": "1004",
    "stop_name": "Financial District",
    "direction_id": "1",
    "trip_type": "full",
    "total_records": 208,
    "time_types": {
      "available": [
        "am_rush",
        "day",
        "night",
        "weekend"
      ],
      "data": {
        "am_rush": {
          "record_count": 33,
          "is_regulatory": true,
          "travel_time_valid": true,
          "topology_flagged": false,
          "topology_critical": false
        },
        "day": {
          "record_count": 60,
          "is_regulatory": true,
          "travel_time_valid": true,
          "topology_flagged": false,
          "topology_critical": false
        },
        "night": {
          "record_count": 63,
          "is_regulatory": true,
          "travel_time_valid": true,
          "topology_flagged": false,
          "topology_critical": false
        },
        "weekend": {
          "record_count": 52,
          "is_regulatory": true,
          "travel_time_valid": true,
          "topology_flagged": false,
          "topology_critical": false
        }
      }
    },
    "gap_info": {
      "has_gap": false,
      "severity": null,
      "violation_type": null,
      "description": null
    },
    "violation_flags": {
      "has_topology_violation": false,
      "has_pattern_violation": false,
      "has_regulatory_violation": false,
      "has_gap_before_this_stop": false,
      "has_any_violation": false,
      "time_types_with_violations": []
    },
    "violation_details_by_time_type": {
      "am_rush": {
        "topology": null,
        "pattern": null,
        "regulatory": null,
        "gap": null,
        "travel_time_unreliable": false
      },
      "day": {
        "topology": null,
        "pattern": null,
        "regulatory": null,
        "gap": null,
        "travel_time_unreliable": false
      },
      "night": {
        "topology": null,
        "pattern": null,
        "regulatory": null,
        "gap": null,
        "travel_time_unreliable": false
      },
      "weekend": {
        "topology": null,
        "pattern": null,
        "regulatory": null,
        "gap": null,
        "travel_time_unreliable": false
      }
    },
    "overall_severity": "none"
  },
  "101_1004_1_partial_3": {
    "route_id": "101",
    "route_name": "Blue Line Express",
    "route_short_name": "Blue",
    "stop_id": "1004",
    "stop_name": "Financial District",
    "direction_id": "1",
    "trip_type": "partial_3",
    "total_records": 115,
    "time_types": {
      "available": [
        "am_rush",
        "day",
        "night",
        "weekend"
      ],
      "data": {
        "am_rush": {
          "record_count": 18,
          "is_regulatory": true,
          "travel_time_valid": true,
          "topology_flagged": false,
          "topology_critical": false
        },
        "day": {
          "record_count": 36,
          "is_regulatory": true,
          "travel_time_valid": true,
          "topology_flagged": false,
          "topology_critical": false
        },
        "night": {
          "record_count": 36,
          "is_regulatory": true,
          "travel_time_valid": true,
          "topology_flagged": false,
          "topology_critical": false
        },
        "weekend": {
          "record_count": 25,
          "is_regulatory": true,
          "travel_time_valid": true,
          "topology_flagged": false,
          "topology_critical": false
        }
      }
    },
    "gap_info": {
      "has_gap": false,
      "severity": null,
      "violation_type": null,
      "description": null
    },
    "violation_flags": {
      "has_topology_violation": false,
      "has_pattern_violation": false,
      "has_regulatory_violation": false,
      "has_gap_before_this_stop": false,
      "has_any_violation": false,
      "time_types_with_violations": []
    },
    "violation_details_by_time_type": {
      "am_rush": {
        "topology": null,
        "pattern": null,
        "regulatory": null,
        "gap": null,
        "travel_time_unreliable": false
      },
      "day": {
        "topology": null,
        "pattern": null,
        "regulatory": null,
        "gap": null,
        "travel_time_unreliable": false
      },
      "night": {
        "topology": null,
        "pattern": null,
        "regulatory": null,
        "gap": null,
        "travel_time_unreliable": false
      },
      "weekend": {
        "topology": null,
        "pattern": null,
        "regulatory": null,
        "gap": null,
        "travel_time_unreliable": false
      }
    },
    "overall_severity": "none"
  },
  "101_1005_0_full": {
    "route_id": "101",
    "route_name": "Blue Line Express",
    "route_short_name": "Blue",
    "stop_id": "1005",
    "stop_name": "Business District",
    "direction_id": "0",
    "trip_type": "full",
    "total_records": 200,
    "time_types": {
      "available": [
        "am_rush",
        "day",
        "night",
        "weekend"
      ],
      "data": {
        "am_rush": {
          "record_count": 30,
          "is_regulatory": true,
          "travel_time_valid": true,
          "topology_flagged": false,
          "topology_critical": false
        },
        "day": {
          "record_count": 60,
          "is_regulatory": true,
          "travel_time_valid": true,
          "topology_flagged": false,
          "topology_critical": false
        },
        "night": {
          "record_count": 60,
          "is_regulatory": true,
          "travel_time_valid": true,
          "topology_flagged": false,
          "topology_critical": false
        },
        "weekend": {
          "record_count": 50,
          "is_regulatory": true,
          "travel_time_valid": true,
          "topology_flagged": false,
          "topology_critical": false
        }
      }
    },
    "gap_info": {
      "has_gap": false,
      "severity": null,
      "violation_type": null,
      "description": null
    },
    "violation_flags": {
      "has_topology_violation": false,
      "has_pattern_violation": false,
      "has_regulatory_violation": false,
      "has_gap_before_this_stop": false,
      "has_any_violation": false,
      "time_types_with_violations": []
    },
    "violation_details_by_time_type": {
      "am_rush": {
        "topology": null,
        "pattern": null,
        "regulatory": null,
        "gap": null,
        "travel_time_unreliable": false
      },
      "day": {
        "topology": null,
        "pattern": null,
        "regulatory": null,
        "gap": null,
        "travel_time_unreliable": false
      },
      "night": {
        "topology": null,
        "pattern": null,
        "regulatory": null,
        "gap": null,
        "travel_time_unreliable": false
      },
      "weekend": {
        "topology": null,
        "pattern": null,
        "regulatory": null,
        "gap": null,
        "travel_time_unreliable": false
      }
    },
    "overall_severity": "none"
  },
  "101_1005_0_partial_3": {
    "route_id": "101",
    "route_name": "Blue Line Express",
    "route_short_name": "Blue",
    "stop_id": "1005",
    "stop_name": "Business District",
    "direction_id": "0",
    "trip_type": "partial_3",
    "total_records": 115,
    "time_types": {
      "available": [
        "am_rush",
        "day",
        "night",
        "weekend"
      ],
      "data": {
        "am_rush": {
          "record_count": 18,
          "is_regulatory": true,
          "travel_time_valid": true,
          "topology_flagged": false,
          "topology_critical": false
        },
        "day": {
          "record_count": 36,
          "is_regulatory": true,
          "travel_time_valid": true,
          "topology_flagged": false,
          "topology_critical": false
        },
        "night": {
          "record_count": 36,
          "is_regulatory": true,
          "travel_time_valid": true,
          "topology_flagged": false,
          "topology_critical": false
        },
        "weekend": {
          "record_count": 25,
          "is_regulatory": true,
          "travel_time_valid": true,
          "topology_flagged": false,
          "topology_critical": false
        }
      }
    },
    "gap_info": {
      "has_gap": false,
      "severity": null,
      "violation_type": null,
      "description": null
    },
    "violation_flags": {
      "has_topology_violation": false,
      "has_pattern_violation": false,
      "has_regulatory_violation": false,
      "has_gap_before_this_stop": false,
      "has_any_violation": false,
      "time_types_with_violations": []
    },
    "violation_details_by_time_type": {
      "am_rush": {
        "topology": null,
        "pattern": null,
        "regulatory": null,
        "gap": null,
        "travel_time_unreliable": false
      },
      "day": {
        "topology": null,
        "pattern": null,
        "regulatory": null,
        "gap": null,
        "travel_time_unreliable": false
      },
      "night": {
        "topology": null,
        "pattern": null,
        "regulatory": null,
        "gap": null,
        "travel_time_unreliable": false
      },
      "weekend": {
        "topology": null,
        "pattern": null,
        "regulatory": null,
        "gap": null,
        "travel_time_unreliable": false
      }
    },
    "overall_severity": "none"
  },
  "101_1006_1_full": {
    "route_id": "101",
    "route_name": "Blue Line Express",
    "route_short_name": "Blue",
    "stop_id": "1006",
    "stop_name": "Business District",
    "direction_id": "1",
    "trip_type": "full",
    "total_records": 208,
    "time_types": {
      "available": [
        "am_rush",
        "day",
        "night",
        "weekend"
      ],
      "data": {
        "am_rush": {
          "record_count": 33,
          "is_regulatory": true,
          "travel_time_valid": true,
          "topology_flagged": false,
          "topology_critical": false
        },
        "day": {
          "record_count": 60,
          "is_regulatory": true,
          "travel_time_valid": true,
          "topology_flagged": false,
          "topology_critical": false
        },
        "night": {
          "record_count": 63,
          "is_regulatory": true,
          "travel_time_valid": true,
          "topology_flagged": false,
          "topology_critical": false
        },
        "weekend": {
          "record_count": 52,
          "is_regulatory": true,
          "travel_time_valid": true,
          "topology_flagged": false,
          "topology_critical": false
        }
      }
    },
    "gap_info": {
      "has_gap": false,
      "severity": null,
      "violation_type": null,
      "description": null
    },
    "violation_flags": {
      "has_topology_violation": false,
      "has_pattern_violation": false,
      "has_regulatory_violation": false,
      "has_gap_before_this_stop": false,
      "has_any_violation": false,
      "time_types_with_violations": []
    },
    "violation_details_by_time_type": {
      "am_rush": {
        "topology": null,
        "pattern": null,
        "regulatory": null,
        "gap": null,
        "travel_time_unreliable": false
      },
      "day": {
        "topology": null,
        "pattern": null,
        "regulatory": null,
        "gap": null,
        "travel_time_unreliable": false
      },
      "night": {
        "topology": null,
        "pattern": null,
        "regulatory": null,
        "gap": null,
        "travel_time_unreliable": false
      },
      "weekend": {
        "topology": null,
        "pattern": null,
        "regulatory": null,
        "gap": null,
        "travel_time_unreliable": false
      }
    },
    "overall_severity": "none"
  },
  "101_1006_1_partial_3": {
    "route_id": "101",
    "route_name": "Blue Line Express",
    "route_short_name": "Blue",
    "stop_id": "1006",
    "stop_name": "Business District",
    "direction_id": "1",
    "trip_type": "partial_3",
    "total_records": 115,
    "time_types": {
      "available": [
        "am_rush",
        "day",
        "night",
        "weekend"
      ],
      "data": {
        "am_rush": {
          "record_count": 18,
          "is_regulatory": true,
          "travel_time_valid": true,
          "topology_flagged": false,
          "topology_critical": false
        },
        "day": {
          "record_count": 36,
          "is_regulatory": true,
          "travel_time_valid": true,
          "topology_flagged": false,
          "topology_critical": false
        },
        "night": {
          "record_count": 36,
          "is_regulatory": true,
          "travel_time_valid": true,
          "topology_flagged": false,
          "topology_critical": false
        },
        "weekend": {
          "record_count": 25,
          "is_regulatory": true,
          "travel_time_valid": true,
          "topology_flagged": false,
          "topology_critical": false
        }
      }
    },
    "gap_info": {
      "has_gap": false,
      "severity": null,
      "violation_type": null,
      "description": null
    },
    "violation_flags": {
      "has_topology_violation": false,
      "has_pattern_violation": false,
      "has_regulatory_violation": false,
      "has_gap_before_this_stop": false,
      "has_any_violation": false,
      "time_types_with_violations": []
    },
    "violation_details_by_time_type": {
      "am_rush": {
        "topology": null,
        "pattern": null,
        "regulatory": null,
        "gap": null,
        "travel_time_unreliable": false
      },
      "day": {
        "topology": null,
        "pattern": null,
        "regulatory": null,
        "gap": null,
        "travel_time_unreliable": false
      },
      "night": {
        "topology": null,
        "pattern": null,
        "regulatory": null,
        "gap": null,
        "travel_time_unreliable": false
      },
      "weekend": {
        "topology": null,
        "pattern": null,
        "regulatory": null,
        "gap": null,
        "travel_time_unreliable": false
      }
    },
    "overall_severity": "none"
  },
  "101_1007_0_full": {
    "route_id": "101",
    "route_name": "Blue Line Express",
    "route_short_name": "Blue",
    "stop_id": "1007",
    "stop_name": "Shopping Center",
    "direction_id": "0",
    "trip_type": "full",
    "total_records": 200,
    "time_types": {
      "available": [
        "am_rush",
        "day",
        "night",
        "weekend"
      ],
      "data": {
        "am_rush": {
          "record_count": 30,
          "is_regulatory": true,
          "travel_time_valid": true,
          "topology_flagged": false,
          "topology_critical": false
        },
        "day": {
          "record_count": 60,
          "is_regulatory": true,
          "travel_time_valid": true,
          "topology_flagged": false,
          "topology_critical": false
        },
        "night": {
          "record_count": 60,
          "is_regulatory": true,
          "travel_time_valid": true,
          "topology_flagged": false,
          "topology_critical": false
        },
        "weekend": {
          "record_count": 50,
          "is_regulatory": true,
          "travel_time_valid": true,
          "topology_flagged": false,
          "topology_critical": false
        }
      }
    },
    "gap_info": {
      "has_gap": false,
      "severity": null,
      "violation_type": null,
      "description": null
    },
    "violation_flags": {
      "has_topology_violation": false,
      "has_pattern_violation": false,
      "has_regulatory_violation": false,
      "has_gap_before_this_stop": false,
      "has_any_violation": false,
      "time_types_with_violations": []
    },
    "violation_details_by_time_type": {
      "am_rush": {
        "topology": null,
        "pattern": null,
        "regulatory": null,
        "gap": null,
        "travel_time_unreliable": false
      },
      "day": {
        "topology": null,
        "pattern": null,
        "regulatory": null,
        "gap": null,
        "travel_time_unreliable": false
      },
      "night": {
        "topology": null,
        "pattern": null,
        "regulatory": null,
        "gap": null,
        "travel_time_unreliable": false
      },
      "weekend": {
        "topology": null,
        "pattern": null,
        "regulatory": null,
        "gap": null,
        "travel_time_unreliable": false
      }
    },
    "overall_severity": "none"
  },
  "101_1007_0_partial_1": {
    "route_id": "101",
    "route_name": "Blue Line Express",
    "route_short_name": "Blue",
    "stop_id": "1007",
    "stop_name": "Shopping Center",
    "direction_id": "0",
    "trip_type": "partial_1",
    "total_records": 76,
    "time_types": {
      "available": [
        "am_rush",
        "day",
        "night",
        "weekend"
      ],
      "data": {
        "am_rush": {
          "record_count": 12,
          "is_regulatory": true,
          "travel_time_valid": false,
          "topology_flagged": false,
          "topology_critical": false
        },
        "day": {
          "record_count": 24,
          "is_regulatory": true,
          "travel_time_valid": false,
          "topology_flagged": false,
          "topology_critical": false
        },
        "night": {
          "record_count": 24,
          "is_regulatory": true,
          "travel_time_valid": false,
          "topology_flagged": false,
          "topology_critical": false
        },
        "weekend": {
          "record_count": 16,
          "is_regulatory": true,
          "travel_time_valid": false,
          "topology_flagged": false,
          "topology_critical": false
        }
      }
    },
    "gap_info": {
      "has_gap": true,
      "severity": "high",
      "violation_type": "gap_before_stop",
      "description": "Gap exists before this stop in partial_1 trips"
    },
    "violation_flags": {
      "has_topology_violation": false,
      "has_pattern_violation": true,
      "has_regulatory_violation": false,
      "has_gap_before_this_stop": true,
      "has_any_violation": true,
      "time_types_with_violations": [
        "am_rush",
        "day",
        "night",
        "weekend"
      ]
    },
    "violation_details_by_time_type": {
      "am_rush": {
        "topology": null,
        "pattern": {
          "severity": "high",
          "proportion": 1.0
        },
        "regulatory": null,
        "gap": {
          "severity": "high",
          "proportion": 1.0
        },
        "travel_time_unreliable": true
      },
      "day": {
        "topology": null,
        "pattern": {
          "severity": "high",
          "proportion": 1.0
        },
        "regulatory": null,
        "gap": {
          "severity": "high",
          "proportion": 1.0
        },
        "travel_time_unreliable": true
      },
      "night": {
        "topology": null,
        "pattern": {
          "severity": "high",
          "proportion": 1.0
        },
        "regulatory": null,
        "gap": {
          "severity": "high",
          "proportion": 1.0
        },
        "travel_time_unreliable": true
      },
      "weekend": {
        "topology": null,
        "pattern": {
          "severity": "high",
          "proportion": 1.0
        },
        "regulatory": null,
        "gap": {
          "severity": "high",
          "proportion": 1.0
        },
        "travel_time_unreliable": true
      }
    },
    "overall_severity": "high"
  },
  "101_1007_0_partial_3": {
    "route_id": "101",
    "route_name": "Blue Line Express",
    "route_short_name": "Blue",
    "stop_id": "1007",
    "stop_name": "Shopping Center",
    "direction_id": "0",
    "trip_type": "partial_3",
    "total_records": 115,
    "time_types": {
      "available": [
        "am_rush",
        "day",
        "night",
        "weekend"
      ],
      "data": {
        "am_rush": {
          "record_count": 18,
          "is_regulatory": true,
          "travel_time_valid": true,
          "topology_flagged": false,
          "topology_critical": false
        },
        "day": {
          "record_count": 36,
          "is_regulatory": true,
          "travel_time_valid": true,
          "topology_flagged": false,
          "topology_critical": false
        },
        "night": {
          "record_count": 36,
          "is_regulatory": true,
          "travel_time_valid": true,
          "topology_flagged": false,
          "topology_critical": false
        },
        "weekend": {
          "record_count": 25,
          "is_regulatory": true,
          "travel_time_valid": true,
          "topology_flagged": false,
          "topology_critical": false
        }
      }
    },
    "gap_info": {
      "has_gap": false,
      "severity": null,
      "violation_type": null,
      "description": null
    },
    "violation_flags": {
      "has_topology_violation": false,
      "has_pattern_violation": false,
      "has_regulatory_violation": false,
      "has_gap_before_this_stop": false,
      "has_any_violation": false,
      "time_types_with_violations": []
    },
    "violation_details_by_time_type": {
      "am_rush": {
        "topology": null,
        "pattern": null,
        "regulatory": null,
        "gap": null,
        "travel_time_unreliable": false
      },
      "day": {
        "topology": null,
        "pattern": null,
        "regulatory": null,
        "gap": null,
        "travel_time_unreliable": false
      },
      "night": {
        "topology": null,
        "pattern": null,
        "regulatory": null,
        "gap": null,
        "travel_time_unreliable": false
      },
      "weekend": {
        "topology": null,
        "pattern": null,
        "regulatory": null,
        "gap": null,
        "travel_time_unreliable": false
      }
    },
    "overall_severity": "none"
  },
  "101_1008_1_full": {
    "route_id": "101",
    "route_name": "Blue Line Express",
    "route_short_name": "Blue",
    "stop_id": "1008",
    "stop_name": "Shopping Center",
    "direction_id": "1",
    "trip_type": "full",
    "total_records": 208,
    "time_types": {
      "available": [
        "am_rush",
        "day",
        "night",
        "weekend"
      ],
      "data": {
        "am_rush": {
          "record_count": 33,
          "is_regulatory": true,
          "travel_time_valid": true,
          "topology_flagged": false,
          "topology_critical": false
        },
        "day": {
          "record_count": 60,
          "is_regulatory": true,
          "travel_time_valid": true,
          "topology_flagged": false,
          "topology_critical": false
        },
        "night": {
          "record_count": 63,
          "is_regulatory": true,
          "travel_time_valid": true,
          "topology_flagged": false,
          "topology_critical": false
        },
        "weekend": {
          "record_count": 52,
          "is_regulatory": true,
          "travel_time_valid": true,
          "topology_flagged": false,
          "topology_critical": false
        }
      }
    },
    "gap_info": {
      "has_gap": false,
      "severity": null,
      "violation_type": null,
      "description": null
    },
    "violation_flags": {
      "has_topology_violation": false,
      "has_pattern_violation": false,
      "has_regulatory_violation": false,
      "has_gap_before_this_stop": false,
      "has_any_violation": false,
      "time_types_with_violations": []
    },
    "violation_details_by_time_type": {
      "am_rush": {
        "topology": null,
        "pattern": null,
        "regulatory": null,
        "gap": null,
        "travel_time_unreliable": false
      },
      "day": {
        "topology": null,
        "pattern": null,
        "regulatory": null,
        "gap": null,
        "travel_time_unreliable": false
      },
      "night": {
        "topology": null,
        "pattern": null,
        "regulatory": null,
        "gap": null,
        "travel_time_unreliable": false
      },
      "weekend": {
        "topology": null,
        "pattern": null,
        "regulatory": null,
        "gap": null,
        "travel_time_unreliable": false
      }
    },
    "overall_severity": "none"
  },
  "101_1008_1_partial_1": {
    "route_id": "101",
    "route_name": "Blue Line Express",
    "route_short_name": "Blue",
    "stop_id": "1008",
    "stop_name": "Shopping Center",
    "direction_id": "1",
    "trip_type": "partial_1",
    "total_records": 76,
    "time_types": {
      "available": [
        "am_rush",
        "day",
        "night",
        "weekend"
      ],
      "data": {
        "am_rush": {
          "record_count": 12,
          "is_regulatory": true,
          "travel_time_valid": false,
          "topology_flagged": false,
          "topology_critical": false
        },
        "day": {
          "record_count": 24,
          "is_regulatory": true,
          "travel_time_valid": false,
          "topology_flagged": false,
          "topology_critical": false
        },
        "night": {
          "record_count": 24,
          "is_regulatory": true,
          "travel_time_valid": false,
          "topology_flagged": false,
          "topology_critical": false
        },
        "weekend": {
          "record_count": 16,
          "is_regulatory": true,
          "travel_time_valid": false,
          "topology_flagged": false,
          "topology_critical": false
        }
      }
    },
    "gap_info": {
      "has_gap": true,
      "severity": "high",
      "violation_type": "gap_before_stop",
      "description": "Gap exists before this stop in partial_1 trips"
    },
    "violation_flags": {
      "has_topology_violation": false,
      "has_pattern_violation": true,
      "has_regulatory_violation": false,
      "has_gap_before_this_stop": true,
      "has_any_violation": true,
      "time_types_with_violations": [
        "am_rush",
        "day",
        "night",
        "weekend"
      ]
    },
    "violation_details_by_time_type": {
      "am_rush": {
        "topology": null,
        "pattern": {
          "severity": "high",
          "proportion": 1.0
        },
        "regulatory": null,
        "gap": {
          "severity": "high",
          "proportion": 1.0
        },
        "travel_time_unreliable": true
      },
      "day": {
        "topology": null,
        "pattern": {
          "severity": "high",
          "proportion": 1.0
        },
        "regulatory": null,
        "gap": {
          "severity": "high",
          "proportion": 1.0
        },
        "travel_time_unreliable": true
      },
      "night": {
        "topology": null,
        "pattern": {
          "severity": "high",
          "proportion": 1.0
        },
        "regulatory": null,
        "gap": {
          "severity": "high",
          "proportion": 1.0
        },
        "travel_time_unreliable": true
      },
      "weekend": {
        "topology": null,
        "pattern": {
          "severity": "high",
          "proportion": 1.0
        },
        "regulatory": null,
        "gap": {
          "severity": "high",
          "proportion": 1.0
        },
        "travel_time_unreliable": true
      }
    },
    "overall_severity": "high"
  },
  "101_1008_1_partial_3": {
    "route_id": "101",
    "route_name": "Blue Line Express",
    "route_short_name": "Blue",
    "stop_id": "1008",
    "stop_name": "Shopping Center",
    "direction_id": "1",
    "trip_type": "partial_3",
    "total_records": 115,
    "time_types": {
      "available": [
        "am_rush",
        "day",
        "night",
        "weekend"
      ],
      "data": {
        "am_rush": {
          "record_count": 18,
          "is_regulatory": true,
          "travel_time_valid": true,
          "topology_flagged": false,
          "topology_critical": false
        },
        "day": {
          "record_count": 36,
          "is_regulatory": true,
          "travel_time_valid": true,
          "topology_flagged": false,
          "topology_critical": false
        },
        "night": {
          "record_count": 36,
          "is_regulatory": true,
          "travel_time_valid": true,
          "topology_flagged": false,
          "topology_critical": false
        },
        "weekend": {
          "record_count": 25,
          "is_regulatory": true,
          "travel_time_valid": true,
          "topology_flagged": false,
          "topology_critical": false
        }
      }
    },
    "gap_info": {
      "has_gap": false,
      "severity": null,
      "violation_type": null,
      "description": null
    },
    "violation_flags": {
      "has_topology_violation": false,
      "has_pattern_violation": false,
      "has_regulatory_violation": false,
      "has_gap_before_this_stop": false,
      "has_any_violation": false,
      "time_types_with_violations": []
    },
    "violation_details_by_time_type": {
      "am_rush": {
        "topology": null,
        "pattern": null,
        "regulatory": null,
        "gap": null,
        "travel_time_unreliable": false
      },
      "day": {
        "topology": null,
        "pattern": null,
        "regulatory": null,
        "gap": null,
        "travel_time_unreliable": false
      },
      "night": {
        "topology": null,
        "pattern": null,
        "regulatory": null,
        "gap": null,
        "travel_time_unreliable": false
      },
      "weekend": {
        "topology": null,
        "pattern": null,
        "regulatory": null,
        "gap": null,
        "travel_time_unreliable": false
      }
    },
    "overall_severity": "none"
  },
  "101_1009_0_full": {
    "route_id": "101",
    "route_name": "Blue Line Express",
    "route_short_name": "Blue",
    "stop_id": "1009",
    "stop_name": "Medical Center",
    "direction_id": "0",
    "trip_type": "full",
    "total_records": 200,
    "time_types": {
      "available": [
        "am_rush",
        "day",
        "night",
        "weekend"
      ],
      "data": {
        "am_rush": {
          "record_count": 30,
          "is_regulatory": true,
          "travel_time_valid": true,
          "topology_flagged": false,
          "topology_critical": false
        },
        "day": {
          "record_count": 60,
          "is_regulatory": true,
          "travel_time_valid": true,
          "topology_flagged": false,
          "topology_critical": false
        },
        "night": {
          "record_count": 60,
          "is_regulatory": true,
          "travel_time_valid": true,
          "topology_flagged": false,
          "topology_critical": false
        },
        "weekend": {
          "record_count": 50,
          "is_regulatory": true,
          "travel_time_valid": true,
          "topology_flagged": false,
          "topology_critical": false
        }
      }
    },
    "gap_info": {
      "has_gap": false,
      "severity": null,
      "violation_type": null,
      "description": null
    },
    "violation_flags": {
      "has_topology_violation": false,
      "has_pattern_violation": false,
      "has_regulatory_violation": true,
      "has_gap_before_this_stop": false,
      "has_any_violation": true,
      "time_types_with_violations": [
        "am_rush",
        "day",
        "night",
        "weekend"
      ]
    },
    "violation_details_by_time_type": {
      "am_rush": {
        "topology": null,
        "pattern": null,
        "regulatory": {
          "severity": "low",
          "proportion": 0.04500000000000004
        },
        "gap": null,
        "travel_time_unreliable": false
      },
      "day": {
        "topology": null,
        "pattern": null,
        "regulatory": {
          "severity": "low",
          "proportion": 0.04500000000000004
        },
        "gap": null,
        "travel_time_unreliable": false
      },
      "night": {
        "topology": null,
        "pattern": null,
        "regulatory": {
          "severity": "low",
          "proportion": 0.04500000000000004
        },
        "gap": null,
        "travel_time_unreliable": false
      },
      "weekend": {
        "topology": null,
        "pattern": null,
        "regulatory": {
          "severity": "low",
          "proportion": 0.04500000000000004
        },
        "gap": null,
        "travel_time_unreliable": false
      }
    },
    "overall_severity": "low"
  },
  "101_1009_0_partial_1": {
    "route_id": "101",
    "route_name": "Blue Line Express",
    "route_short_name": "Blue",
    "stop_id": "1009",
    "stop_name": "Medical Center",
    "direction_id": "0",
    "trip_type": "partial_1",
    "total_records": 76,
    "time_types": {
      "available": [
        "am_rush",
        "day",
        "night",
        "weekend"
      ],
      "data": {
        "am_rush": {
          "record_count": 12,
          "is_regulatory": true,
          "travel_time_valid": false,
          "topology_flagged": false,
          "topology_critical": false
        },
        "day": {
          "record_count": 24,
          "is_regulatory": true,
          "travel_time_valid": false,
          "topology_flagged": false,
          "topology_critical": false
        },
        "night": {
          "record_count": 24,
          "is_regulatory": true,
          "travel_time_valid": false,
          "topology_flagged": false,
          "topology_critical": false
        },
        "weekend": {
          "record_count": 16,
          "is_regulatory": true,
          "travel_time_valid": false,
          "topology_flagged": false,
          "topology_critical": false
        }
      }
    },
    "gap_info": {
      "has_gap": true,
      "severity": "high",
      "violation_type": "gap_before_stop",
      "description": "Gap exists before this stop in partial_1 trips"
    },
    "violation_flags": {
      "has_topology_violation": false,
      "has_pattern_violation": true,
      "has_regulatory_violation": false,
      "has_gap_before_this_stop": true,
      "has_any_violation": true,
      "time_types_with_violations": [
        "am_rush",
        "day",
        "night",
        "weekend"
      ]
    },
    "violation_details_by_time_type": {
      "am_rush": {
        "topology": null,
        "pattern": {
          "severity": "high",
          "proportion": 1.0
        },
        "regulatory": null,
        "gap": {
          "severity": "high",
          "proportion": 1.0
        },
        "travel_time_unreliable": true
      },
      "day": {
        "topology": null,
        "pattern": {
          "severity": "high",
          "proportion": 1.0
        },
        "regulatory": null,
        "gap": {
          "severity": "high",
          "proportion": 1.0
        },
        "travel_time_unreliable": true
      },
      "night": {
        "topology": null,
        "pattern": {
          "severity": "high",
          "proportion": 1.0
        },
        "regulatory": null,
        "gap": {
          "severity": "high",
          "proportion": 1.0
        },
        "travel_time_unreliable": true
      },
      "weekend": {
        "topology": null,
        "pattern": {
          "severity": "high",
          "proportion": 1.0
        },
        "regulatory": null,
        "gap": {
          "severity": "high",
          "proportion": 1.0
        },
        "travel_time_unreliable": true
      }
    },
    "overall_severity": "high"
  },
  "101_1010_1_full": {
    "route_id": "101",
    "route_name": "Blue Line Express",
    "route_short_name": "Blue",
    "stop_id": "1010",
    "stop_name": "Medical Center",
    "direction_id": "1",
    "trip_type": "full",
    "total_records": 208,
    "time_types": {
      "available": [
        "am_rush",
        "day",
        "night",
        "weekend"
      ],
      "data": {
        "am_rush": {
          "record_count": 33,
          "is_regulatory": false,
          "travel_time_valid": true,
          "topology_flagged": false,
          "topology_critical": false
        },
        "day": {
          "record_count": 60,
          "is_regulatory": false,
          "travel_time_valid": true,
          "topology_flagged": false,
          "topology_critical": false
        },
        "night": {
          "record_count": 63,
          "is_regulatory": false,
          "travel_time_valid": true,
          "topology_flagged": false,
          "topology_critical": false
        },
        "weekend": {
          "record_count": 52,
          "is_regulatory": false,
          "travel_time_valid": true,
          "topology_flagged": false,
          "topology_critical": false
        }
      }
    },
    "gap_info": {
      "has_gap": false,
      "severity": null,
      "violation_type": null,
      "description": null
    },
    "violation_flags": {
      "has_topology_violation": false,
      "has_pattern_violation": false,
      "has_regulatory_violation": false,
      "has_gap_before_this_stop": false,
      "has_any_violation": false,
      "time_types_with_violations": []
    },
    "violation_details_by_time_type": {
      "am_rush": {
        "topology": null,
        "pattern": null,
        "regulatory": null,
        "gap": null,
        "travel_time_unreliable": false
      },
      "day": {
        "topology": null,
        "pattern": null,
        "regulatory": null,
        "gap": null,
        "travel_time_unreliable": false
      },
      "night": {
        "topology": null,
        "pattern": null,
        "regulatory": null,
        "gap": null,
        "travel_time_unreliable": false
      },
      "weekend": {
        "topology": null,
        "pattern": null,
        "regulatory": null,
        "gap": null,
        "travel_time_unreliable": false
      }
    },
    "overall_severity": "none"
  },
  "101_1010_1_partial_1": {
    "route_id": "101",
    "route_name": "Blue Line Express",
    "route_short_name": "Blue",
    "stop_id": "1010",
    "stop_name": "Medical Center",
    "direction_id": "1",
    "trip_type": "partial_1",
    "total_records": 76,
    "time_types": {
      "available": [
        "am_rush",
        "day",
        "night",
        "weekend"
      ],
      "data": {
        "am_rush": {
          "record_count": 12,
          "is_regulatory": true,
          "travel_time_valid": false,
          "topology_flagged": false,
          "topology_critical": false
        },
        "day": {
          "record_count": 24,
          "is_regulatory": true,
          "travel_time_valid": false,
          "topology_flagged": false,
          "topology_critical": false
        },
        "night": {
          "record_count": 24,
          "is_regulatory": true,
          "travel_time_valid": false,
          "topology_flagged": false,
          "topology_critical": false
        },
        "weekend": {
          "record_count": 16,
          "is_regulatory": true,
          "travel_time_valid": false,
          "topology_flagged": false,
          "topology_critical": false
        }
      }
    },
    "gap_info": {
      "has_gap": true,
      "severity": "high",
      "violation_type": "gap_before_stop",
      "description": "Gap exists before this stop in partial_1 trips"
    },
    "violation_flags": {
      "has_topology_violation": false,
      "has_pattern_violation": true,
      "has_regulatory_violation": false,
      "has_gap_before_this_stop": true,
      "has_any_violation": true,
      "time_types_with_violations": [
        "am_rush",
        "day",
        "night",
        "weekend"
      ]
    },
    "violation_details_by_time_type": {
      "am_rush": {
        "topology": null,
        "pattern": {
          "severity": "high",
          "proportion": 1.0
        },
        "regulatory": null,
        "gap": {
          "severity": "high",
          "proportion": 1.0
        },
        "travel_time_unreliable": true
      },
      "day": {
        "topology": null,
        "pattern": {
          "severity": "high",
          "proportion": 1.0
        },
        "regulatory": null,
        "gap": {
          "severity": "high",
          "proportion": 1.0
        },
        "travel_time_unreliable": true
      },
      "night": {
        "topology": null,
        "pattern": {
          "severity": "high",
          "proportion": 1.0
        },
        "regulatory": null,
        "gap": {
          "severity": "high",
          "proportion": 1.0
        },
        "travel_time_unreliable": true
      },
      "weekend": {
        "topology": null,
        "pattern": {
          "severity": "high",
          "proportion": 1.0
        },
        "regulatory": null,
        "gap": {
          "severity": "high",
          "proportion": 1.0
        },
        "travel_time_unreliable": true
      }
    },
    "overall_severity": "high"
  },
  "101_2001_0_full": {
    "route_id": "101",
    "route_name": "Blue Line Express",
    "route_short_name": "Blue",
    "stop_id": "2001",
    "stop_name": "University Campus",
    "direction_id": "0",
    "trip_type": "full",
    "total_records": 200,
    "time_types": {
      "available": [
        "am_rush",
        "day",
        "night",
        "weekend"
      ],
      "data": {
        "am_rush": {
          "record_count": 30,
          "is_regulatory": true,
          "travel_time_valid": true,
          "topology_flagged": false,
          "topology_critical": false
        },
        "day": {
          "record_count": 60,
          "is_regulatory": true,
          "travel_time_valid": true,
          "topology_flagged": false,
          "topology_critical": false
        },
        "night": {
          "record_count": 60,
          "is_regulatory": true,
          "travel_time_valid": true,
          "topology_flagged": false,
          "topology_critical": false
        },
        "weekend": {
          "record_count": 50,
          "is_regulatory": true,
          "travel_time_valid": true,
          "topology_flagged": false,
          "topology_critical": false
        }
      }
    },
    "gap_info": {
      "has_gap": false,
      "severity": null,
      "violation_type": null,
      "description": null
    },
    "violation_flags": {
      "has_topology_violation": false,
      "has_pattern_violation": false,
      "has_regulatory_violation": false,
      "has_gap_before_this_stop": false,
      "has_any_violation": false,
      "time_types_with_violations": []
    },
    "violation_details_by_time_type": {
      "am_rush": {
        "topology": null,
        "pattern": null,
        "regulatory": null,
        "gap": null,
        "travel_time_unreliable": false
      },
      "day": {
        "topology": null,
        "pattern": null,
        "regulatory": null,
        "gap": null,
        "travel_time_unreliable": false
      },
      "night": {
        "topology": null,
        "pattern": null,
        "regulatory": null,
        "gap": null,
        "travel_time_unreliable": false
      },
      "weekend": {
        "topology": null,
        "pattern": null,
        "regulatory": null,
        "gap": null,
        "travel_time_unreliable": false
      }
    },
    "overall_severity": "none"
  },
  "101_2001_0_partial_1": {
    "route_id": "101",
    "route_name": "Blue Line Express",
    "route_short_name": "Blue",
    "stop_id": "2001",
    "stop_name": "University Campus",
    "direction_id": "0",
    "trip_type": "partial_1",
    "total_records": 76,
    "time_types": {
      "available": [
        "am_rush",
        "day",
        "night",
        "weekend"
      ],
      "data": {
        "am_rush": {
          "record_count": 12,
          "is_regulatory": true,
          "travel_time_valid": false,
          "topology_flagged": false,
          "topology_critical": false
        },
        "day": {
          "record_count": 24,
          "is_regulatory": true,
          "travel_time_valid": false,
          "topology_flagged": false,
          "topology_critical": false
        },
        "night": {
          "record_count": 24,
          "is_regulatory": true,
          "travel_time_valid": false,
          "topology_flagged": false,
          "topology_critical": false
        },
        "weekend": {
          "record_count": 16,
          "is_regulatory": true,
          "travel_time_valid": false,
          "topology_flagged": false,
          "topology_critical": false
        }
      }
    },
    "gap_info": {
      "has_gap": true,
      "severity": "high",
      "violation_type": "gap_before_stop",
      "description": "Gap exists before this stop in partial_1 trips"
    },
    "violation_flags": {
      "has_topology_violation": false,
      "has_pattern_violation": true,
      "has_regulatory_violation": false,
      "has_gap_before_this_stop": true,
      "has_any_violation": true,
      "time_types_with_violations": [
        "am_rush",
        "day",
        "night",
        "weekend"
      ]
    },
    "violation_details_by_time_type": {
      "am_rush": {
        "topology": null,
        "pattern": {
          "severity": "high",
          "proportion": 1.0
        },
        "regulatory": null,
        "gap": {
          "severity": "high",
          "proportion": 1.0
        },
        "travel_time_unreliable": true
      },
      "day": {
        "topology": null,
        "pattern": {
          "severity": "high",
          "proportion": 1.0
        },
        "regulatory": null,
        "gap": {
          "severity": "high",
          "proportion": 1.0
        },
        "travel_time_unreliable": true
      },
      "night": {
        "topology": null,
        "pattern": {
          "severity": "high",
          "proportion": 1.0
        },
        "regulatory": null,
        "gap": {
          "severity": "high",
          "proportion": 1.0
        },
        "travel_time_unreliable": true
      },
      "weekend": {
        "topology": null,
        "pattern": {
          "severity": "high",
          "proportion": 1.0
        },
        "regulatory": null,
        "gap": {
          "severity": "high",
          "proportion": 1.0
        },
        "travel_time_unreliable": true
      }
    },
    "overall_severity": "high"
  },
  "101_2001_0_partial_3": {
    "route_id": "101",
    "route_name": "Blue Line Express",
    "route_short_name": "Blue",
    "stop_id": "2001",
    "stop_name": "University Campus",
    "direction_id": "0",
    "trip_type": "partial_3",
    "total_records": 115,
    "time_types": {
      "available": [
        "am_rush",
        "day",
        "night",
        "weekend"
      ],
      "data": {
        "am_rush": {
          "record_count": 18,
          "is_regulatory": true,
          "travel_time_valid": true,
          "topology_flagged": false,
          "topology_critical": false
        },
        "day": {
          "record_count": 36,
          "is_regulatory": true,
          "travel_time_valid": true,
          "topology_flagged": false,
          "topology_critical": false
        },
        "night": {
          "record_count": 36,
          "is_regulatory": true,
          "travel_time_valid": true,
          "topology_flagged": false,
          "topology_critical": false
        },
        "weekend": {
          "record_count": 25,
          "is_regulatory": true,
          "travel_time_valid": true,
          "topology_flagged": false,
          "topology_critical": false
        }
      }
    },
    "gap_info": {
      "has_gap": false,
      "severity": null,
      "violation_type": null,
      "description": null
    },
    "violation_flags": {
      "has_topology_violation": false,
      "has_pattern_violation": false,
      "has_regulatory_violation": false,
      "has_gap_before_this_stop": false,
      "has_any_violation": false,
      "time_types_with_violations": []
    },
    "violation_details_by_time_type": {
      "am_rush": {
        "topology": null,
        "pattern": null,
        "regulatory": null,
        "gap": null,
        "travel_time_unreliable": false
      },
      "day": {
        "topology": null,
        "pattern": null,
        "regulatory": null,
        "gap": null,
        "travel_time_unreliable": false
      },
      "night": {
        "topology": null,
        "pattern": null,
        "regulatory": null,
        "gap": null,
        "travel_time_unreliable": false
      },
      "weekend": {
        "topology": null,
        "pattern": null,
        "regulatory": null,
        "gap": null,
        "travel_time_unreliable": false
      }
    },
    "overall_severity": "none"
  },
  "101_2001_1_full": {
    "route_id": "101",
    "route_name": "Blue Line Express",
    "route_short_name": "Blue",
    "stop_id": "2001",
    "stop_name": "University Campus",
    "direction_id": "1",
    "trip_type": "full",
    "total_records": 208,
    "time_types": {
      "available": [
        "am_rush",
        "day",
        "night",
        "weekend"
      ],
      "data": {
        "am_rush": {
          "record_count": 33,
          "is_regulatory": true,
          "travel_time_valid": true,
          "topology_flagged": false,
          "topology_critical": false
        },
        "day": {
          "record_count": 60,
          "is_regulatory": true,
          "travel_time_valid": true,
          "topology_flagged": false,
          "topology_critical": false
        },
        "night": {
          "record_count": 63,
          "is_regulatory": true,
          "travel_time_valid": true,
          "topology_flagged": false,
          "topology_critical": false
        },
        "weekend": {
          "record_count": 52,
          "is_regulatory": true,
          "travel_time_valid": true,
          "topology_flagged": false,
          "topology_critical": false
        }
      }
    },
    "gap_info": {
      "has_gap": false,
      "severity": null,
      "violation_type": null,
      "description": null
    },
    "violation_flags": {
      "has_topology_violation": false,
      "has_pattern_violation": false,
      "has_regulatory_violation": false,
      "has_gap_before_this_stop": false,
      "has_any_violation": false,
      "time_types_with_violations": []
    },
    "violation_details_by_time_type": {
      "am_rush": {
        "topology": null,
        "pattern": null,
        "regulatory": null,
        "gap": null,
        "travel_time_unreliable": false
      },
      "day": {
        "topology": null,
        "pattern": null,
        "regulatory": null,
        "gap": null,
        "travel_time_unreliable": false
      },
      "night": {
        "topology": null,
        "pattern": null,
        "regulatory": null,
        "gap": null,
        "travel_time_unreliable": false
      },
      "weekend": {
        "topology": null,
        "pattern": null,
        "regulatory": null,
        "gap": null,
        "travel_time_unreliable": false
      }
    },
    "overall_severity": "none"
  },
  "101_2001_1_partial_1": {
    "route_id": "101",
    "route_name": "Blue Line Express",
    "route_short_name": "Blue",
    "stop_id": "2001",
    "stop_name": "University Campus",
    "direction_id": "1",
    "trip_type": "partial_1",
    "total_records": 76,
    "time_types": {
      "available": [
        "am_rush",
        "day",
        "night",
        "weekend"
      ],
      "data": {
        "am_rush": {
          "record_count": 12,
          "is_regulatory": true,
          "travel_time_valid": false,
          "topology_flagged": false,
          "topology_critical": false
        },
        "day": {
          "record_count": 24,
          "is_regulatory": true,
          "travel_time_valid": false,
          "topology_flagged": false,
          "topology_critical": false
        },
        "night": {
          "record_count": 24,
          "is_regulatory": true,
          "travel_time_valid": false,
          "topology_flagged": false,
          "topology_critical": false
        },
        "weekend": {
          "record_count": 16,
          "is_regulatory": true,
          "travel_time_valid": false,
          "topology_flagged": false,
          "topology_critical": false
        }
      }
    },
    "gap_info": {
      "has_gap": true,
      "severity": "high",
      "violation_type": "gap_before_stop",
      "description": "Gap exists before this stop in partial_1 trips"
    },
    "violation_flags": {
      "has_topology_violation": false,
      "has_pattern_violation": true,
      "has_regulatory_violation": false,
      "has_gap_before_this_stop": true,
      "has_any_violation": true,
      "time_types_with_violations": [
        "am_rush",
        "day",
        "night",
        "weekend"
      ]
    },
    "violation_details_by_time_type": {
      "am_rush": {
        "topology": null,
        "pattern": {
          "severity": "high",
          "proportion": 1.0
        },
        "regulatory": null,
        "gap": {
          "severity": "high",
          "proportion": 1.0
        },
        "travel_time_unreliable": true
      },
      "day": {
        "topology": null,
        "pattern": {
          "severity": "high",
          "proportion": 1.0
        },
        "regulatory": null,
        "gap": {
          "severity": "high",
          "proportion": 1.0
        },
        "travel_time_unreliable": true
      },
      "night": {
        "topology": null,
        "pattern": {
          "severity": "high",
          "proportion": 1.0
        },
        "regulatory": null,
        "gap": {
          "severity": "high",
          "proportion": 1.0
        },
        "travel_time_unreliable": true
      },
      "weekend": {
        "topology": null,
        "pattern": {
          "severity": "high",
          "proportion": 1.0
        },
        "regulatory": null,
        "gap": {
          "severity": "high",
          "proportion": 1.0
        },
        "travel_time_unreliable": true
      }
    },
    "overall_severity": "high"
  },
  "101_2001_1_partial_3": {
    "route_id": "101",
    "route_name": "Blue Line Express",
    "route_short_name": "Blue",
    "stop_id": "2001",
    "stop_name": "University Campus",
    "direction_id": "1",
    "trip_type": "partial_3",
    "total_records": 115,
    "time_types": {
      "available": [
        "am_rush",
        "day",
        "night",
        "weekend"
      ],
      "data": {
        "am_rush": {
          "record_count": 18,
          "is_regulatory": true,
          "travel_time_valid": true,
          "topology_flagged": false,
          "topology_critical": false
        },
        "day": {
          "record_count": 36,
          "is_regulatory": true,
          "travel_time_valid": true,
          "topology_flagged": false,
          "topology_critical": false
        },
        "night": {
          "record_count": 36,
          "is_regulatory": true,
          "travel_time_valid": true,
          "topology_flagged": false,
          "topology_critical": false
        },
        "weekend": {
          "record_count": 25,
          "is_regulatory": true,
          "travel_time_valid": true,
          "topology_flagged": false,
          "topology_critical": false
        }
      }
    },
    "gap_info": {
      "has_gap": false,
      "severity": null,
      "violation_type": null,
      "description": null
    },
    "violation_flags": {
      "has_topology_violation": false,
      "has_pattern_violation": false,
      "has_regulatory_violation": false,
      "has_gap_before_this_stop": false,
      "has_any_violation": false,
      "time_types_with_violations": []
    },
    "violation_details_by_time_type": {
      "am_rush": {
        "topology": null,
        "pattern": null,
        "regulatory": null,
        "gap": null,
        "travel_time_unreliable": false
      },
      "day": {
        "topology": null,
        "pattern": null,
        "regulatory": null,
        "gap": null,
        "travel_time_unreliable": false
      },
      "night": {
        "topology": null,
        "pattern": null,
        "regulatory": null,
        "gap": null,
        "travel_time_unreliable": false
      },
      "weekend": {
        "topology": null,
        "pattern": null,
        "regulatory": null,
        "gap": null,
        "travel_time_unreliable": false
      }
    },
    "overall_severity": "none"
  },
  "101_3001_0_full": {
    "route_id": "101",
    "route_name": "Blue Line Express",
    "route_short_name": "Blue",
    "stop_id": "3001",
    "stop_name": "City Hall",
    "direction_id": "0",
    "trip_type": "full",
    "total_records": 200,
    "time_types": {
      "available": [
        "am_rush",
        "day",
        "night",
        "weekend"
      ],
      "data": {
        "am_rush": {
          "record_count": 30,
          "is_regulatory": true,
          "travel_time_valid": true,
          "topology_flagged": false,
          "topology_critical": false
        },
        "day": {
          "record_count": 60,
          "is_regulatory": true,
          "travel_time_valid": true,
          "topology_flagged": false,
          "topology_critical": false
        },
        "night": {
          "record_count": 60,
          "is_regulatory": true,
          "travel_time_valid": true,
          "topology_flagged": false,
          "topology_critical": false
        },
        "weekend": {
          "record_count": 50,
          "is_regulatory": true,
          "travel_time_valid": true,
          "topology_flagged": false,
          "topology_critical": false
        }
      }
    },
    "gap_info": {
      "has_gap": false,
      "severity": null,
      "violation_type": null,
      "description": null
    },
    "violation_flags": {
      "has_topology_violation": false,
      "has_pattern_violation": false,
      "has_regulatory_violation": false,
      "has_gap_before_this_stop": false,
      "has_any_violation": false,
      "time_types_with_violations": []
    },
    "violation_details_by_time_type": {
      "am_rush": {
        "topology": null,
        "pattern": null,
        "regulatory": null,
        "gap": null,
        "travel_time_unreliable": false
      },
      "day": {
        "topology": null,
        "pattern": null,
        "regulatory": null,
        "gap": null,
        "travel_time_unreliable": false
      },
      "night": {
        "topology": null,
        "pattern": null,
        "regulatory": null,
        "gap": null,
        "travel_time_unreliable": false
      },
      "weekend": {
        "topology": null,
        "pattern": null,
        "regulatory": null,
        "gap": null,
        "travel_time_unreliable": false
      }
    },
    "overall_severity": "none"
  },
  "101_3002_1_full": {
    "route_id": "101",
    "route_name": "Blue Line Express",
    "route_short_name": "Blue",
    "stop_id": "3002",
    "stop_name": "City Hall",
    "direction_id": "1",
    "trip_type": "full",
    "total_records": 208,
    "time_types": {
      "available": [
        "am_rush",
        "day",
        "night",
        "weekend"
      ],
      "data": {
        "am_rush": {
          "record_count": 33,
          "is_regulatory": true,
          "travel_time_valid": true,
          "topology_flagged": false,
          "topology_critical": false
        },
        "day": {
          "record_count": 60,
          "is_regulatory": true,
          "travel_time_valid": true,
          "topology_flagged": false,
          "topology_critical": false
        },
        "night": {
          "record_count": 63,
          "is_regulatory": true,
          "travel_time_valid": true,
          "topology_flagged": false,
          "topology_critical": false
        },
        "weekend": {
          "record_count": 52,
          "is_regulatory": true,
          "travel_time_valid": true,
          "topology_flagged": false,
          "topology_critical": false
        }
      }
    },
    "gap_info": {
      "has_gap": false,
      "severity": null,
      "violation_type": null,
      "description": null
    },
    "violation_flags": {
      "has_topology_violation": false,
      "has_pattern_violation": false,
      "has_regulatory_violation": false,
      "has_gap_before_this_stop": false,
      "has_any_violation": false,
      "time_types_with_violations": []
    },
    "violation_details_by_time_type": {
      "am_rush": {
        "topology": null,
        "pattern": null,
        "regulatory": null,
        "gap": null,
        "travel_time_unreliable": false
      },
      "day": {
        "topology": null,
        "pattern": null,
        "regulatory": null,
        "gap": null,
        "travel_time_unreliable": false
      },
      "night": {
        "topology": null,
        "pattern": null,
        "regulatory": null,
        "gap": null,
        "travel_time_unreliable": false
      },
      "weekend": {
        "topology": null,
        "pattern": null,
        "regulatory": null,
        "gap": null,
        "travel_time_unreliable": false
      }
    },
    "overall_severity": "none"
  }
}